nectl/__init__.py
nectl/checks/__init__.py
nectl/checks/cli.py
nectl/checks/plugins.py
nectl/cli.py
nectl/configs/__init__.py
nectl/configs/cli.py
nectl/configs/drivers/__init__.py
nectl/configs/drivers/basedriver.py
nectl/configs/drivers/napalmdriver.py
nectl/configs/drivers/utils.py
nectl/configs/render.py
nectl/configs/template_utils.py
nectl/configs/templates.py
nectl/configs/utils.py
nectl/datatree/__init__.py
nectl/datatree/actions.py
nectl/datatree/cli.py
nectl/datatree/facts_utils.py
nectl/datatree/hosts.py
nectl/exceptions.py
nectl/logging.py
nectl/nectl.py
nectl/settings.py
nectl-0.19.6.dist-info/METADATA
nectl-0.19.6.dist-info/WHEEL
nectl-0.19.6.dist-info/entry_points.txt
nectl-0.19.6.dist-info/licenses/COPYING
nectl-0.19.6.dist-info/RECORD
