Metadata-Version: 2.4
Name: nectl
Version: 0.19.6
Summary: An end-to-end Python-based Infrastructure as Code framework for network automation and orchestration.
License-File: COPYING
Keywords: Network automation,Network orchestration,Network engineering,Automation,Orchestration
Author: Adam Kirchberger
Author-email: adamkirchberger@users.noreply.github.com
Requires-Python: >=3.10,<4.0
Classifier: Programming Language :: Python :: 3
Classifier: Programming Language :: Python :: 3.10
Classifier: Programming Language :: Python :: 3.11
Classifier: Programming Language :: Python :: 3.12
Classifier: Programming Language :: Python :: 3.13
Classifier: Programming Language :: Python :: 3.14
Requires-Dist: click (>=8.3.1,<9.0.0)
Requires-Dist: coloredlogs (>=15.0.1,<16.0.0)
Requires-Dist: dpath (>=2.0.5,<3.0.0)
Requires-Dist: ipaddress (>=1.0.23,<2.0.0)
Requires-Dist: napalm (>=5.0.0,<6.0.0)
Requires-Dist: pydantic (>=1.8,<3)
Requires-Dist: pydantic-settings (>=2.12.0,<3.0.0)
Requires-Dist: pytest (>=9.0.0,<10.0.0)
Requires-Dist: pytest-forked (>=1.3.0,<2.0.0)
Requires-Dist: tabulate (>=0.9.0,<0.10.0)
Project-URL: Documentation, https://nectl.netlify.app
Project-URL: Repository, https://github.com/adamkirchberger/nectl
